CHANGES.rst
MANIFEST.in
README.rst
setup.py
js/__init__.py
js.jquery_fileupload.egg-info/PKG-INFO
js.jquery_fileupload.egg-info/SOURCES.txt
js.jquery_fileupload.egg-info/dependency_links.txt
js.jquery_fileupload.egg-info/entry_points.txt
js.jquery_fileupload.egg-info/namespace_packages.txt
js.jquery_fileupload.egg-info/not-zip-safe
js.jquery_fileupload.egg-info/requires.txt
js.jquery_fileupload.egg-info/top_level.txt
js/jquery_fileupload/__init__.py
js/jquery_fileupload/test_jquery_fileupload.txt
js/jquery_fileupload/resources/css/demo-ie8.css
js/jquery_fileupload/resources/css/demo.css
js/jquery_fileupload/resources/css/jquery.fileupload-noscript.css
js/jquery_fileupload/resources/css/jquery.fileupload-ui-noscript.css
js/jquery_fileupload/resources/css/jquery.fileupload-ui.css
js/jquery_fileupload/resources/css/jquery.fileupload.css
js/jquery_fileupload/resources/css/style.css
js/jquery_fileupload/resources/img/loading.gif
js/jquery_fileupload/resources/img/progressbar.gif
js/jquery_fileupload/resources/js/app.js
js/jquery_fileupload/resources/js/jquery.fileupload-angular.js
js/jquery_fileupload/resources/js/jquery.fileupload-audio.js
js/jquery_fileupload/resources/js/jquery.fileupload-image.js
js/jquery_fileupload/resources/js/jquery.fileupload-jquery-ui.js
js/jquery_fileupload/resources/js/jquery.fileupload-process.js
js/jquery_fileupload/resources/js/jquery.fileupload-ui.js
js/jquery_fileupload/resources/js/jquery.fileupload-validate.js
js/jquery_fileupload/resources/js/jquery.fileupload-video.js
js/jquery_fileupload/resources/js/jquery.fileupload.js
js/jquery_fileupload/resources/js/jquery.iframe-transport.js
js/jquery_fileupload/resources/js/main.js
js/jquery_fileupload/resources/js/cors/jquery.postmessage-transport.js
js/jquery_fileupload/resources/js/cors/jquery.xdr-transport.js
js/jquery_fileupload/resources/js/vendor/jquery.ui.widget.js