Metadata-Version: 1.1
Name: js.jquery-fileupload
Version: 9.7.0b1
Summary: Fanstatic packaging of jquery.fileupload.js.
Home-page: https://github.com/tmassman/js.jquery_fileupload
Author: Thomas Massmann
Author-email: thomas.massmann@it-spir.it
License: BSD
Download-URL: http://pypi.python.org/pypi/js.jquery_fileupload
Platform: UNKNOWN
